vscode_spot_check.py
vscode_spot_check-0.0.1.dist-info/METADATA
vscode_spot_check-0.0.1.dist-info/WHEEL
vscode_spot_check-0.0.1.dist-info/top_level.txt
vscode_spot_check-0.0.1.dist-info/RECORD
